MANIFEST.in
README.rst
setup.py
docs/_build/html/searchindex.js
docs/_build/html/_static/doctools.js
docs/_build/html/_static/jquery-1.11.1.js
docs/_build/html/_static/jquery.js
docs/_build/html/_static/searchtools.js
docs/_build/html/_static/sidebar.js
docs/_build/html/_static/underscore-1.3.1.js
docs/_build/html/_static/underscore.js
docs/_build/html/_static/websupport.js
openag/__init__.py
openag/categories.py
openag/couch.py
openag/db_names.py
openag/models.py
openag/utils.py
openag/var_types.py
openag.egg-info/PKG-INFO
openag.egg-info/SOURCES.txt
openag.egg-info/dependency_links.txt
openag.egg-info/entry_points.txt
openag.egg-info/requires.txt
openag.egg-info/top_level.txt
openag/_design/__init__.py
openag/_design/environmental_data_point/validate_doc_update.js
openag/_design/environmental_data_point/filters/by_variable.js
openag/_design/environmental_data_point/lists/csv.js
openag/_design/environmental_data_point/views/by_timestamp/map.js
openag/_design/environmental_data_point/views/by_variable/map.js
openag/_design/environmental_data_point/views/by_variable/reduce.js
openag/_design/firmware_module/validate_doc_update.js
openag/_design/firmware_module_type/validate_doc_update.js
openag/_design/recipes/validate_doc_update.js
openag/_design/software_module/validate_doc_update.js
openag/_design/software_module/views/by_type/map.js
openag/_design/software_module_type/validate_doc_update.js
openag/_design/software_module_type/views/by_group/map.js
openag/cli/__init__.py
openag/cli/config.py
openag/cli/utils.py
openag/cli/cloud/__init__.py
openag/cli/cloud/db.py
openag/cli/cloud/farm.py
openag/cli/cloud/user.py
openag/cli/db/__init__.py
openag/cli/db/db_config.py
openag/cli/firmware/__init__.py
openag/cli/firmware/base.py
openag/cli/firmware/plugins/__init__.py
openag/cli/firmware/plugins/csv.py
openag/cli/firmware/plugins/ros.py
tests/__init__.py
tests/test_couch.py
tests/test_cli/__init__.py
tests/test_cli/test_cloud.py
tests/test_cli/test_codegen.py
tests/test_cli/test_config.py
tests/test_cli/test_db.py
tests/test_cli/test_farm.py
tests/test_cli/test_user.py
tests/test_cli/test_utils.py