Metadata-Version: 1.1
Name: openag
Version: 0.1.5
Summary: Core Python package for the OpenAg software stack
Home-page: https://github.com/OpenAgInitiative/openag_python
Author: Open Agriculture Initiative
Author-email: UNKNOWN
License: GPL
Platform: UNKNOWN
Classifier: Development Status :: 3 - Alpha
Classifier: Intended Audience :: Developers
Classifier: License :: OSI Approved :: GNU General Public License v3 (GPLv3)
Classifier: Programming Language :: Python :: 2.7
